RA_Package/__init__.py
RA_Package/file_io.py
RA_Package/last_erg_writer.py
RA_Package/logger.py
RA_Package/mail_log.py
RA_Package/math.py
RA_Package-1.0.3.dist-info/LICENSE
RA_Package-1.0.3.dist-info/METADATA
RA_Package-1.0.3.dist-info/WHEEL
RA_Package-1.0.3.dist-info/top_level.txt
RA_Package-1.0.3.dist-info/RECORD
