Metadata-Version: 2.1
Name: RA-Package
Version: 1.0.3
Summary: Backend Library for RA-Rechner
Home-page: https://github.com/manuraffl30/RA_Rechner
Author: Manuel Alexander Christoph Raffl
Author-email: manuraffl003@gmail.com
License: UNKNOWN
Project-URL: Bug Tracker, https://github.com/manuraffl30/RA_Rechner/issues
Platform: UNKNOWN
Classifier: Programming Language :: Python :: 3
Classifier: License :: OSI Approved :: MIT License
Classifier: Operating System :: OS Independent
License-File: LICENSE
